siquant/__init__.py
siquant/dimensions.py
siquant/exceptions.py
siquant/quantities.py
siquant/units.py
siquant/util.py
siquant/systems/__init__.py
siquant/systems/imperial.py
siquant/systems/si.py
siquant-3.0.5.dist-info/LICENSE
siquant-3.0.5.dist-info/METADATA
siquant-3.0.5.dist-info/WHEEL
siquant-3.0.5.dist-info/top_level.txt
siquant-3.0.5.dist-info/zip-safe
siquant-3.0.5.dist-info/RECORD
