Metadata-Version: 2.1
Name: siquant
Version: 3.0.5
Summary: SI units and quantities library
Home-page: https://github.com/keystonetowersystems/siquant
Author: Greg Echelberger
Author-email: greg@keystonetowersystems.com
License: UNKNOWN
Platform: UNKNOWN
Classifier: Programming Language :: Python
Classifier: License :: OSI Approved :: MIT License
Classifier: Topic :: Scientific/Engineering
Classifier: Operating System :: OS Independent
Classifier: Intended Audience :: Developers
Classifier: Intended Audience :: Science/Research
Provides-Extra: dev
Requires-Dist: sphinx; extra == 'dev'
Requires-Dist: coverage; extra == 'dev'
Requires-Dist: pytest; extra == 'dev'
Requires-Dist: pre-commit; extra == 'dev'
Provides-Extra: docs
Requires-Dist: sphinx; extra == 'docs'
Provides-Extra: tests
Requires-Dist: coverage; extra == 'tests'
Requires-Dist: pytest; extra == 'tests'
